sdrips/__init__.py
sdrips/canal_water_distribution.py
sdrips/cmd_area_creation.py
sdrips/cmd_area_stats.py
sdrips/cmd_config.py
sdrips/evapotranspiration.py
sdrips/gfs_processing.py
sdrips/percolation.py
sdrips/precipitation.py
sdrips/run_sdrips.py
sdrips/sen_corr_evapotranspiration.py
sdrips/stn_corr_evapotranspiration.py
sdrips/tiff_preprocess.py
sdrips/cli/__init__.py
sdrips/cli/sdrips_init.py
sdrips/cli/sdrips_test.py
sdrips/utils/__init__.py
sdrips/utils/clean.py
sdrips/utils/ee_utils.py
sdrips/utils/initialize.py
sdrips/utils/logging_utils.py
sdrips/utils/make_directory.py
sdrips/utils/sensor_utils.py
sdrips/utils/utils.py
sdrips/utils/weather_station_utils.py
sdrips-0.0.1.dist-info/licenses/LICENSE
sdrips-0.0.1.dist-info/METADATA
sdrips-0.0.1.dist-info/WHEEL
sdrips-0.0.1.dist-info/entry_points.txt
sdrips-0.0.1.dist-info/top_level.txt
sdrips-0.0.1.dist-info/RECORD
