Metadata-Version: 2.4
Name: sdrips
Version: 0.0.1
Summary: A Package For Optimizing Surface Water Irrigation using Satellite Remote Sensing
Home-page: https://github.com/UW-SASWE/sDRIPS
Author: Shahzaib Khan
Author-email: Shahzaib Khan <khan.shahzaib1007@gmail.com>
License:                     GNU GENERAL PUBLIC LICENSE
Project-URL: Homepage, https://github.com/UW-SASWE/sDRIPS
Project-URL: Repository, https://github.com/UW-SASWE/sDRIPS/tree/main
Project-URL: Bug Tracker, https://github.com/UW-SASWE/sDRIPS/issues
Requires-Python: >=3.7
License-File: LICENSE
Requires-Dist: beautifulsoup4
Requires-Dist: contextily
Requires-Dist: earthengine-api
Requires-Dist: filelock
Requires-Dist: geemap
Requires-Dist: geopandas
Requires-Dist: geopy
Requires-Dist: matplotlib
Requires-Dist: networkx
Requires-Dist: numpy
Requires-Dist: pandas
Requires-Dist: paramiko
Requires-Dist: pykrige
Requires-Dist: pyproj
Requires-Dist: pytest
Requires-Dist: pyyaml
Requires-Dist: rasterio
Requires-Dist: requests
Requires-Dist: rioxarray
Requires-Dist: ruamel.yaml
Requires-Dist: scikit-learn
Requires-Dist: scipy
Requires-Dist: shapely
Requires-Dist: tqdm
Requires-Dist: xarray
Requires-Dist: cartopy
Requires-Dist: google-cloud-resource-manager
Requires-Dist: pycrs
Dynamic: license-file
